setup.py
distributions_804/Binomialdistribution.py
distributions_804/Gaussiandistribution.py
distributions_804/Generaldistribution.py
distributions_804/__init__.py
distributions_804.egg-info/PKG-INFO
distributions_804.egg-info/SOURCES.txt
distributions_804.egg-info/dependency_links.txt
distributions_804.egg-info/not-zip-safe
distributions_804.egg-info/top_level.txt